atmodeller/LICENSE
atmodeller/__init__.py
atmodeller/classes.py
atmodeller/constants.py
atmodeller/containers.py
atmodeller/engine.py
atmodeller/engine_vmap.py
atmodeller/interfaces.py
atmodeller/output.py
atmodeller/output_core.py
atmodeller/solvers.py
atmodeller/type_aliases.py
atmodeller/utilities.py
atmodeller/eos/__init__.py
atmodeller/eos/_aggregators.py
atmodeller/eos/_chabrier.py
atmodeller/eos/_holland_powell.py
atmodeller/eos/_holley.py
atmodeller/eos/_reid_connolly.py
atmodeller/eos/_saxena.py
atmodeller/eos/_vanderwaals.py
atmodeller/eos/_wang.py
atmodeller/eos/_zhang_duan.py
atmodeller/eos/core.py
atmodeller/eos/library.py
atmodeller/eos/data/__init__.py
atmodeller/eos/data/chabrier/TABLEEOS_2021_TP_Y0275_v1
atmodeller/eos/data/chabrier/TABLEEOS_2021_TP_Y0292_v1
atmodeller/eos/data/chabrier/TABLEEOS_2021_TP_Y0297_v1
atmodeller/eos/data/chabrier/TABLE_HE_TP_v1
atmodeller/eos/data/chabrier/TABLE_H_TP_v1
atmodeller/solubility/__init__.py
atmodeller/solubility/_carbon_species.py
atmodeller/solubility/_hydrogen_species.py
atmodeller/solubility/_other_species.py
atmodeller/solubility/_sulfur_species.py
atmodeller/solubility/core.py
atmodeller/solubility/library.py
atmodeller/thermodata/__init__.py
atmodeller/thermodata/_redox_buffers.py
atmodeller/thermodata/core.py
atmodeller/thermodata/data/critical_data.txt
atmodeller/thermodata/data/nasa_glenn_coefficients.txt
atmodeller-0.11.0.dist-info/METADATA
atmodeller-0.11.0.dist-info/WHEEL
atmodeller-0.11.0.dist-info/licenses/LICENSE
atmodeller-0.11.0.dist-info/RECORD
